flaxmodels/__init__.py
flaxmodels/utils.py
flaxmodels/few_shot_gan_adaption/__init__.py
flaxmodels/few_shot_gan_adaption/discriminator.py
flaxmodels/few_shot_gan_adaption/generator.py
flaxmodels/few_shot_gan_adaption/ops.py
flaxmodels/gpt2/__init__.py
flaxmodels/gpt2/gpt2.py
flaxmodels/gpt2/ops.py
flaxmodels/gpt2/tokenizer.py
flaxmodels/gpt2/third_party/__init__.py
flaxmodels/gpt2/third_party/huggingface_transformers/__init__.py
flaxmodels/gpt2/third_party/huggingface_transformers/configuration_gpt2.py
flaxmodels/gpt2/third_party/huggingface_transformers/utils/__init__.py
flaxmodels/gpt2/third_party/huggingface_transformers/utils/file_utils.py
flaxmodels/gpt2/third_party/huggingface_transformers/utils/hf_api.py
flaxmodels/gpt2/third_party/huggingface_transformers/utils/logging.py
flaxmodels/gpt2/third_party/huggingface_transformers/utils/tokenization_utils.py
flaxmodels/gpt2/third_party/huggingface_transformers/utils/tokenization_utils_base.py
flaxmodels/gpt2/third_party/huggingface_transformers/utils/versions.py
flaxmodels/resnet/__init__.py
flaxmodels/resnet/ops.py
flaxmodels/resnet/resnet.py
flaxmodels/stylegan2/__init__.py
flaxmodels/stylegan2/discriminator.py
flaxmodels/stylegan2/generator.py
flaxmodels/stylegan2/ops.py
flaxmodels/vgg/__init__.py
flaxmodels/vgg/vgg.py
flaxmodels-0.1.3.dist-info/METADATA
flaxmodels-0.1.3.dist-info/WHEEL
flaxmodels-0.1.3.dist-info/top_level.txt
flaxmodels-0.1.3.dist-info/RECORD
