Metadata-Version: 2.1
Name: flaxmodels
Version: 0.1.3
Summary: A collection of pretrained models in Flax.
Home-page: https://github.com/matthias-wright/flaxmodels
Author: Matthias Wright
License: Each model has an individual license.
Requires-Python: >=3.6
Requires-Dist: h5py >=2.10.0
Requires-Dist: numpy >=1.19.5
Requires-Dist: requests >=2.23.0
Requires-Dist: packaging >=20.9
Requires-Dist: dataclasses >=0.6
Requires-Dist: filelock >=3.0.12
Requires-Dist: jax >=0.3
Requires-Dist: jaxlib
Requires-Dist: flax >=0.4.0
Requires-Dist: Pillow >=7.1.2
Requires-Dist: regex >=2021.4.4
Requires-Dist: tqdm >=4.60.0
Provides-Extra: testing
Requires-Dist: pytest ; extra == 'testing'
